CHANGES.txt
MANIFEST.in
README.rst
requirements.txt
setup.py
HookTest/__init__.py
HookTest/build.py
HookTest/cmd.py
HookTest/test.py
HookTest/units.py
HookTest.egg-info/PKG-INFO
HookTest.egg-info/SOURCES.txt
HookTest.egg-info/dependency_links.txt
HookTest.egg-info/entry_points.txt
HookTest.egg-info/not-zip-safe
HookTest.egg-info/requires.txt
HookTest.egg-info/top_level.txt
HookTest/capitains_units/__init__.py
HookTest/capitains_units/cts.py
HookTest/resources/epidoc.rng
HookTest/resources/tei.rng
tests/__init__.py
tests/test_build.py
tests/test_finder.py
tests/test_run.py
tests/test_test.py
tests/test_units.py
tests/test_cts/__init__.py
tests/test_cts/test_single_text_methods.py
tests/test_cts/mocks/__init__.py
tests/test_cts/mocks/xmllang_data.py