Metadata-Version: 2.1
Name: HookTest
Version: 1.2.3
Summary: Hook Test Script for GitHub/CapiTainS repositories
Home-page: http://github.com/Capitains/HookTest
Author: Thibault Clérice, Matt Munson
Author-email: leponteineptique@gmail.com
License: Mozilla Public License Version 2.0
Platform: UNKNOWN
Classifier: Topic :: Software Development :: Quality Assurance
Classifier: Topic :: Software Development :: Testing
Classifier: Topic :: Software Development :: Version Control
Classifier: Topic :: Text Processing :: Markup :: XML
Classifier: Topic :: Text Processing :: General
Classifier: License :: OSI Approved :: Mozilla Public License 2.0 (MPL 2.0)
